README.md
setup.py
sshsocksvpn/__init__.py
sshsocksvpn/__main__.py
sshsocksvpn/config.py
sshsocksvpn/vpn.py
sshsocksvpn.egg-info/PKG-INFO
sshsocksvpn.egg-info/SOURCES.txt
sshsocksvpn.egg-info/dependency_links.txt
sshsocksvpn.egg-info/entry_points.txt
sshsocksvpn.egg-info/requires.txt
sshsocksvpn.egg-info/top_level.txt