Metadata-Version: 1.0
Name: sshsocksvpn
Version: 0.2
Summary: Simple badvpn-tun2socks wrapper
Home-page: https://github.com/grimpy/sshsocksvpn
Author: Jo De Boeck
Author-email: deboeck.jo@gmail.com
License: GPLv2
Platform: UNKNOWN
